vimwiki_cli/__init__.py
vimwiki_cli/__main__.py
vimwiki_cli/context.py
vimwiki_cli/diary.py
vimwiki_cli/editor.py
vimwiki_cli/tags.py
vimwiki_cli/wiki.py
vimwiki_cli-1.2.0.dist-info/LICENSE
vimwiki_cli-1.2.0.dist-info/METADATA
vimwiki_cli-1.2.0.dist-info/WHEEL
vimwiki_cli-1.2.0.dist-info/entry_points.txt
vimwiki_cli-1.2.0.dist-info/top_level.txt
vimwiki_cli-1.2.0.dist-info/RECORD
