Metadata-Version: 2.1
Name: vimwiki-cli
Version: 1.2.0
Summary: Vimwiki Command-Line Interface
Home-page: https://github.com/sstallion/vimwiki-cli
Author: Steven Stallion
Author-email: sstallion@gmail.com
License: BSD-2-Clause
Keywords: cli vim vimwiki wiki
Classifier: Development Status :: 5 - Production/Stable
Classifier: Environment :: Console
Classifier: Intended Audience :: End Users/Desktop
Classifier: License :: OSI Approved :: BSD License
Classifier: Operating System :: OS Independent
Classifier: Programming Language :: Python
Classifier: Programming Language :: Python :: 3
Classifier: Programming Language :: Python :: 3.7
Classifier: Programming Language :: Python :: 3.8
Classifier: Programming Language :: Python :: 3.9
Classifier: Programming Language :: Python :: 3.10
Classifier: Programming Language :: Python :: 3.11
Classifier: Topic :: Text Editors
Classifier: Topic :: Text Editors :: Documentation
License-File: LICENSE
Requires-Dist: click >=7.1
Provides-Extra: release
Requires-Dist: build >=0.3.0 ; extra == 'release'
Requires-Dist: bump2version >=1.0.0 ; extra == 'release'
Requires-Dist: keepachangelog >=0.5.0 ; extra == 'release'
Provides-Extra: test
Requires-Dist: coverage ~=5.5 ; extra == 'test'
Requires-Dist: mock ~=3.0 ; extra == 'test'
Requires-Dist: pycodestyle ~=2.7 ; extra == 'test'
Requires-Dist: pytest >=4.6 ; extra == 'test'
Requires-Dist: pytest-cov >=2.11 ; extra == 'test'
